tok/__init__.py
tok-0.1.14.dist-info/METADATA
tok-0.1.14.dist-info/RECORD
tok-0.1.14.dist-info/WHEEL
tok-0.1.14.dist-info/top_level.txt
tokens/__init__.py
